pydometer/__init__.py
pydometer/filters.py
pydometer/example_data/example.bin
pydometer-2019.2.8.dist-info/DESCRIPTION.rst
pydometer-2019.2.8.dist-info/METADATA
pydometer-2019.2.8.dist-info/RECORD
pydometer-2019.2.8.dist-info/WHEEL
pydometer-2019.2.8.dist-info/metadata.json
pydometer-2019.2.8.dist-info/top_level.txt
